fsspec_union/__init__.py
fsspec_union/fs.py
fsspec_union/tests/conftest.py
fsspec_union/tests/test_all.py
fsspec_union/tests/test_fs.py
fsspec_union/tests/local1/masked.py
fsspec_union/tests/local1/my_local_file1.py
fsspec_union/tests/local2/masked.py
fsspec_union/tests/local2/my_local_file2.py
fsspec_union-0.1.0.dist-info/METADATA
fsspec_union-0.1.0.dist-info/WHEEL
fsspec_union-0.1.0.dist-info/entry_points.txt
fsspec_union-0.1.0.dist-info/licenses/LICENSE
fsspec_union-0.1.0.dist-info/RECORD
